{"sections":{"main":{"type":"product-main-alt","blocks":{"model_size_ebD7cb":{"type":"model_size","settings":{"label":"Model size","value":"Tygo is 1,85m en draagt maat M","conditional_render":"true"}},"title_b3BBQK":{"type":"title","settings":{}},"price_CcJHTk":{"type":"price","settings":{"sale_prefix":"Je bespaard"}},"tags_mckUwa":{"type":"tags","settings":{}},"excerpt_DrDALB":{"type":"excerpt","settings":{"desc":"{{ product.metafields.custom.short_description | metafield_tag }}"}},"variant_picker_HtJhGB":{"type":"variant_picker","settings":{}},"buy_buttons_XGjKAg":{"type":"buy_buttons","settings":{"text":"Add to cart","sold_out_text":"Uitverkocht"}},"usp_slider_UcjgU3":{"type":"usp_slider","settings":{"usp_1":"Voor 23:00 besteld, zelfde werkdag verstuurd","usp_2":"Gratis verzending vanaf €50,-","usp_3":"Beoordeeld met 4.8\/5.0 uit 500 reviews","usp_4":"","usp_5":""}},"bought_together_RqPWyK":{"type":"bought_together","settings":{"title":"Complete your look","subtitle":"Combine these items with your selected item to complete your look.","products":"{{ product.metafields[\"globo--filter--product_recommendation\"].bought_together_products.value }}"}}},"block_order":["model_size_ebD7cb","title_b3BBQK","price_CcJHTk","tags_mckUwa","excerpt_DrDALB","variant_picker_HtJhGB","buy_buttons_XGjKAg","usp_slider_UcjgU3","bought_together_RqPWyK"],"settings":{"enable_zoom":true}},"product_features_WLqrgx":{"type":"product-features","name":"Product Features","settings":{"product":"{{ product }}"}},"product_specifications_b4JJXF":{"type":"product-specifications","name":"Product Specifications","settings":{"title":"Product specifications","product":"{{ product }}"}},"product_description_zk3H8x":{"type":"product-description","blocks":{"accordion_item_M4LNb6":{"type":"accordion_item","settings":{"title":"Description","content":"<ul><li>Highly functional and padded men’s ski jacket<\/li><li>Elastic outer material for optimum freedom of movement<\/li><li>Breathable, waterproof & windproof ZIENER AQUASHIELD® membrane<\/li><li>Waterproof rating: 10,000 mm \/ Breathability: 10,000 g\/m²\/24h<\/li><li>PFAS-free waterproofing<\/li><li>bluesign® certified outer fabric<\/li><li>100 g\/m² lightweight, breathable insulation for balanced warmth<\/li><li>Keeps you warm even in damp conditions<\/li><li>Elastic inner lining for extra comfort and flexibility<\/li><li>Fixed, adjustable functional hood<\/li><li>Elastic inner sleeve cuffs for a secure fit<\/li><li>Fixed snow skirt to keep snow out<\/li><li>Underarm ventilation zippers for added airflow<\/li><li>Multiple practical pockets for ski goggles, sunglasses & smartphone<\/li><li>Ski pass pocket and zipped chest pocket included<\/li><li>Ideal combination of comfort, protection & performance on the slopes<\/li><\/ul>","open":true}},"accordion_item_PyjCpa":{"type":"accordion_item","settings":{"title":"Technology","content":"<p>Content<\/p>","open":false}},"accordion_item_G9WMqx":{"type":"accordion_item","settings":{"title":"More info","content":"<p>Content<\/p>","open":false}}},"block_order":["accordion_item_M4LNb6","accordion_item_PyjCpa","accordion_item_G9WMqx"],"name":"Product Description","settings":{"image":"shopify:\/\/shop_images\/Container_6.webp"}},"product_slider_RiAbAb":{"type":"product-slider","name":"Products Slider","settings":{"title":"New arrivals","desc":"<p>30% Discount for black Friday valid till 30th November<\/p>","btn_text":"","btn_url":"shopify:\/\/collections\/all","products":["demo-tobin-z-jacket-man","guard-z-gtx-gore-grip-pr-glove-man","juha-z-midlayer-man","tidal-z-jacket-man","tobina-z-jacket-lady"]}}},"order":["main","product_features_WLqrgx","product_specifications_b4JJXF","product_description_zk3H8x","product_slider_RiAbAb"]}